cerbeyra/__init__.py
cerbeyra/apis.py
cerbeyra/exceptions.py
cerbeyra/utils.py
cerbeyra/src/__init__.py
cerbeyra/src/base.py
cerbeyra/src/types.py
cerbeyra/src/cerbeyra_client/__init__.py
cerbeyra/src/cerbeyra_client/cerbeyra_client.py
cerbeyra/src/cerbeyra_client/token.py
cerbeyra/src/dto/__init__.py
cerbeyra/src/dto/asset.py
cerbeyra/src/dto/cerbeyra_index.py
cerbeyra/src/dto/client.py
cerbeyra/src/dto/host.py
cerbeyra/src/dto/network_host_vuln.py
cerbeyra/src/dto/network_report.py
cerbeyra/src/dto/probe.py
cerbeyra/src/dto/scan_results.py
cerbeyra/src/dto/sensor.py
cerbeyra/src/dto/technical_info.py
cerbeyra/src/dto/web_host_vuln.py
cerbeyra/src/dto/web_report.py
cerbeyra/src/dto/collections/__init__.py
cerbeyra/src/dto/collections/asset_collection.py
cerbeyra/src/dto/collections/host_collection.py
cerbeyra/src/dto/collections/result_collection.py
cerbeyra/src/dto/collections/vuln_collection.py
cerbeyra/src/dto/commons/__init__.py
cerbeyra/src/dto/commons/collection.py
cerbeyra/src/dto/commons/item.py
cerbeyra/src/dto/commons/va_item.py
cerbeyra/src/dto/commons/va_report.py
cerbeyra/src/dto/factories/__init__.py
cerbeyra/src/dto/factories/factories.py
cerbeyra/src/services/__init__.py
cerbeyra/src/services/assets.py
cerbeyra/src/services/base.py
cerbeyra/src/services/iot.py
cerbeyra/src/services/overall.py
cerbeyra/src/services/partners.py
cerbeyra/src/services/reports.py
cerbeyra/src/services/scans.py
cerbeyra/src/services/vulnerabilities.py
cerbeyra_api-1.1b1.dist-info/LICENSE
cerbeyra_api-1.1b1.dist-info/METADATA
cerbeyra_api-1.1b1.dist-info/WHEEL
cerbeyra_api-1.1b1.dist-info/top_level.txt
cerbeyra_api-1.1b1.dist-info/zip-safe
cerbeyra_api-1.1b1.dist-info/RECORD
