Metadata-Version: 2.1
Name: cerbeyra-api
Version: 1.1b1
Summary: This library provides a high level interface for interacting with Cerbeyra’s APIs and retrieving cyber-threat’s information from them. Through such API’s, it is possible to get clues regarding vulnerability assessments, cyber feeds, governance, threat intelligence and much more. Additionally, all these information are enclosed in an index named Cerbeyra index) which is an objective evaluation of the overall cyber risk.
Author-email: Cerbeyra Dev Team <info@cerbeyra.com>
Project-URL: Homepage, https://cerbeyra.com
Classifier: Programming Language :: Python :: 3
Classifier: License :: OSI Approved :: MIT License
Classifier: Operating System :: OS Independent
Requires-Python: >=3.7
License-File: LICENSE
Requires-Dist: openpyxl (>=3.0.10)
Requires-Dist: requests (>=2.28.2)
